tailwhip/__init__.py
tailwhip/__main__.py
tailwhip/cli.py
tailwhip/configuration.py
tailwhip/configuration.toml
tailwhip/files.py
tailwhip/process.py
tailwhip/sorting.py
tailwhip/tests/__init__.py
tailwhip/tests/test_cli.py
tailwhip/tests/test_file_finder.py
tailwhip/tests/test_patterns.py
tailwhip/tests/test_sorting.py
tailwhip/tests/test_stdin.py
tailwhip/tests/test_write.py
tailwhip-0.11.0.dist-info/licenses/LICENSE
tailwhip-0.11.0.dist-info/METADATA
tailwhip-0.11.0.dist-info/WHEEL
tailwhip-0.11.0.dist-info/entry_points.txt
tailwhip-0.11.0.dist-info/top_level.txt
tailwhip-0.11.0.dist-info/RECORD
