Metadata-Version: 2.4
Name: tailwhip
Version: 0.11.0
Summary: A pure Python Tailwind CSS class sorter that works with any HTML or CSS file, including Django templates and other template languages.
Author-email: Martin Mahner <martin@mahner.org>
License-Expression: MIT
Project-URL: Homepage, https://github.com/bartTC/tailwhip/
Project-URL: Repository, https://github.com/bartTC/tailwhip/
Project-URL: Documentation, https://github.com/bartTC/tailwhip/blob/main/README.md
Project-URL: Changelog, https://github.com/bartTC/tailwhip/blob/main/CHANGELOG.md
Project-URL: Bug Tracker, https://github.com/bartTC/tailwhip/issues
Classifier: Development Status :: 3 - Alpha
Classifier: Programming Language :: Python :: 3 :: Only
Classifier: Environment :: Web Environment
Classifier: Intended Audience :: Developers
Classifier: Operating System :: OS Independent
Classifier: Programming Language :: Python
Classifier: Programming Language :: Python :: 3.11
Classifier: Programming Language :: Python :: 3.12
Classifier: Programming Language :: Python :: 3.13
Classifier: Programming Language :: Python :: 3.14
Classifier: Topic :: Internet :: WWW/HTTP
Classifier: Topic :: Software Development :: Libraries :: Python Modules
Requires-Python: >=3.11
License-File: LICENSE
Requires-Dist: dynaconf
Requires-Dist: rich
Requires-Dist: typer
Requires-Dist: wcmatch
Dynamic: license-file
